{
  "runtime": "Default",
  "defaultVariables": null,
  "documentGenerator": {
    "fromDocument": {
      "url": "https://localhost:5002/swagger/gamesession-v1/swagger.json",
      "output": null
    }
  },
  "codeGenerators": {
    "openApiToTypeScriptClient": {
      "className": "GameSessionClient",
      "moduleName": "",
      "namespace": "",
      "typeScriptVersion": 4.7,
      "template": "Fetch",
      "promiseType": "Promise",
      "httpClass": "HttpClient",
      "useSingleton": false,
      "singletonInstance": "instance",
      "wrapDtoExceptions": true,
      "exceptionClass": "ApiException",
      "wrapResponses": false,
      "generateResponseClasses": true,
      "responseClass": "SwaggerResponse",
      "protectedMethods": [],
      "configurationClass": null,
      "useTransformOptionsMethod": false,
      "useTransformResultMethod": false,
      "generateOptionalParameters": false,
      "exportTypes": true,
      "generateDataContracts": true,
      "generateNullableReferenceTypes": false,
      "generateDefaultValues": true,
      "generateDataContractEnums": false,
      "wrapNullableParameters": false,
      "injectHttpClient": false,
      "disposeHttpClient": false,
      "useHttpClientCreationMethod": false,
      "httpClientType": "HttpClient",
      "useHttpRequestMessageCreationMethod": false,
      "useBaseUrl": false,
      "generateBaseUrlProperty": false,
      "generateConstructors": true,
      "generateDefaultConstructor": true,
      "generateCloneMethod": false,
      "generateJsonMethods": false,
      "enforceDateOnly": false,
      "templateDirectory": null,
      "typeScriptGeneratorSettings": {
        "typeScriptVersion": 4.7,
        "moduleName": "",
        "namespace": "",
        "enumNameGenerator": {
          "type": "Default"
        },
        "enumValueNameGenerator": {
          "type": "Default"
        },
        "propertyNameGenerator": {
          "type": "Default"
        },
        "typeNameGenerator": {
          "type": "Default"
        },
        "template": "Default",
        "templateDirectory": null,
        "typeScriptConvertPropertyName": false,
        "typeScriptConvertEnumPropertyName": false,
        "enumStyle": "Enum",
        "enumAsString": false,
        "enumAsStringLiteralTypes": false,
        "stringLiteralTypesInsteadOfEnums": false,
        "generateCloneMethod": false,
        "generateDefaultValues": true,
        "generateDataContracts": true,
        "generateDataContractEnums": false,
        "exportTypes": true,
        "exportExtensionCode": true,
        "generateJsonMethods": false,
        "typeScriptNumberType": "Number",
        "typeScriptDateTimeType": "Date",
        "typeScriptDateType": "String",
        "typeScriptTimeType": "String",
        "typeScriptTimeSpanType": "String",
        "typeScriptDurationType": "String",
        "typeScriptArrayType": "Array",
        "typeScriptArrayInstanceType": "Array",
        "typeScriptDictionaryType": "{ [key: string]: any }",
        "typeScriptDictionaryInstanceType": "{ [key: string]: any }",
        "typeScriptObjectType": "any",
        "typeScriptAnyType": "any",
        "typeScriptDateTypeFormat": "String",
        "typeScriptTimeTypeFormat": "String",
        "typeScriptTimeSpanTypeFormat": "String",
        "typeScriptDurationTypeFormat": "String",
        "typeScriptDateTimeTypeFormat": "String",
        "typeScriptNewLine": "CRLF",
        "typeScriptStyle": "SingleQuotes",
        "typeScriptExtendedClasses": [],
        "typeScriptExtendedInterfaces": [],
        "typeScriptModuleResolution": "Node",
        "typeScriptStrictNullChecks": false,
        "typeScriptStrict": false,
        "typeScriptReadonly": false,
        "typeScriptNumberEnum": false,
        "typeScriptEnumStyle": "Enum",
        "typeScriptEnumAsStringLiteralTypes": false,
        "typeScriptStringLiteralTypesInsteadOfEnums": false,
        "typeScriptSuppressImplicitAnyIndexErrors": false,
        "typeScriptSuppressExcessPropertyErrors": false,
        "typeScriptSuppressMissingPropertiesErrors": false,
        "typeScriptNullValue": "Undefined",
        "typeScriptUndefinedValue": "Undefined",
        "typeScriptDateTypeFormat": "String",
        "typeScriptTimeTypeFormat": "String",
        "typeScriptTimeSpanTypeFormat": "String",
        "typeScriptDurationTypeFormat": "String",
        "typeScriptDateTimeTypeFormat": "String",
        "typeScriptNewLine": "CRLF",
        "typeScriptStyle": "SingleQuotes",
        "typeScriptExtendedClasses": [],
        "typeScriptExtendedInterfaces": [],
        "typeScriptModuleResolution": "Node",
        "typeScriptStrictNullChecks": false,
        "typeScriptStrict": false,
        "typeScriptReadonly": false,
        "typeScriptNumberEnum": false,
        "typeScriptEnumStyle": "Enum",
        "typeScriptEnumAsStringLiteralTypes": false,
        "typeScriptStringLiteralTypesInsteadOfEnums": false,
        "typeScriptSuppressImplicitAnyIndexErrors": false,
        "typeScriptSuppressExcessPropertyErrors": false,
        "typeScriptSuppressMissingPropertiesErrors": false,
        "typeScriptNullValue": "Undefined",
        "typeScriptUndefinedValue": "Undefined"
      },
      "output": "src/services/generated-client.ts"
    }
  }
} 